{"cameraMode":{"drawMode":0,"name":"Shaded","section":"Shading Mode"},"sceneLighting":true,"audioPlay":false,"sceneViewState":{"m_AlwaysRefresh":false,"showFog":true,"showSkybox":true,"showFlares":true,"showImageEffects":true,"showParticleSystems":true,"showVisualEffectGraphs":true,"m_FxEnabled":true},"in2DMode":false,"pivot":{"x":-8.013755798339844,"y":3.561789035797119,"z":28.24307632446289},"rotation":{"x":-0.1409778892993927,"y":0.08182723820209503,"z":-0.011506503447890282,"w":-0.9867026805877686},"size":23.383638381958009,"orthographic":false}